codegen.py
setup.py
templetize.py
templetize.egg-info/PKG-INFO
templetize.egg-info/SOURCES.txt
templetize.egg-info/dependency_links.txt
templetize.egg-info/requires.txt
templetize.egg-info/top_level.txt