Metadata-Version: 1.0
Name: templetize
Version: 2014.09.21
Summary: Templetize is a script to convert a file or a directory (recursively) to a template for codegen. It is bundled with a simple code generator module to expand these templates.
Home-page: UNKNOWN
Author: Nico Hoffmann
Author-email: info@maxdoom.com
License: BSD
Keywords: templating code generator
Platform: UNKNOWN
